Aianalytics/__init__.py
Aianalytics/a.py
Aianalytics-2.0.1.dist-info/LICENSE.txt
Aianalytics-2.0.1.dist-info/METADATA
Aianalytics-2.0.1.dist-info/WHEEL
Aianalytics-2.0.1.dist-info/top_level.txt
Aianalytics-2.0.1.dist-info/RECORD
